{
  "/docs-ef8": {
    "__comp": "1be78505",
    "__context": {
      "plugin": "4cbec7d6"
    },
    "versionMetadata": "935f2afb"
  },
  "/docs/CopyrightNotice-efb": {
    "__comp": "17896441",
    "content": "3fe628f9"
  },
  "/docs/help-781": {
    "__comp": "17896441",
    "content": "49491008"
  },
  "/docs/intro-aed": {
    "__comp": "17896441",
    "content": "0e384e19"
  },
  "/docs/mc-34a": {
    "__comp": "17896441",
    "content": "32a82e20"
  },
  "/docs/talk-ff6": {
    "__comp": "17896441",
    "content": "f34e7908"
  },
  "/-7c5": {
    "__comp": "c4f5d8e4",
    "__context": {
      "plugin": "143b6241"
    },
    "config": "5e9f5e1a"
  }
}